{
  "$schema": "https://ui.shadcn.com/schema/registry-item.json",
  "name": "input-group-demo",
  "registryDependencies": [
    "@herocn/input-group"
  ],
  "files": [
    {
      "path": "components/examples/input-group-demo.tsx",
      "content": "import { Search } from \"lucide-react\";\n\nimport {\n  InputGroup,\n  InputGroupAddon,\n  InputGroupInput,\n} from \"@/components/ui/input-group\";\n\nexport default function InputGroupDemo() {\n  return (\n    <InputGroup className=\"max-w-xs\">\n      <InputGroupInput placeholder=\"Search...\" />\n      <InputGroupAddon>\n        <Search />\n      </InputGroupAddon>\n      <InputGroupAddon align=\"inline-end\">12 results</InputGroupAddon>\n    </InputGroup>\n  );\n}\n",
      "type": "registry:example"
    }
  ],
  "type": "registry:example"
}