{
  "$schema": "https://ui.shadcn.com/schema/registry-item.json",
  "name": "input-group-rtl",
  "registryDependencies": [
    "field",
    "input-group",
    "spinner"
  ],
  "files": [
    {
      "path": "components/examples/input-group-rtl.tsx",
      "content": "\"use client\";\r\n\r\nimport { Search } from \"lucide-react\";\r\n\r\nimport {\r\n  type Translations,\r\n  useTranslation,\r\n} from \"@/components/language-selector\";\r\nimport {\r\n  Field,\r\n  FieldDescription,\r\n  FieldGroup,\r\n  FieldLabel,\r\n} from \"@/components/ui/field\";\r\nimport {\r\n  InputGroup,\r\n  InputGroupAddon,\r\n  InputGroupButton,\r\n  InputGroupInput,\r\n  InputGroupText,\r\n  InputGroupTextarea,\r\n} from \"@/components/ui/input-group\";\r\nimport { Spinner } from \"@/components/ui/spinner\";\r\n\r\nconst translations: Translations = {\r\n  en: {\r\n    dir: \"ltr\",\r\n    values: {\r\n      placeholder: \"Search...\",\r\n      results: \"12 results\",\r\n      searching: \"Searching...\",\r\n      saving: \"Saving...\",\r\n      savingChanges: \"Saving changes...\",\r\n      textareaLabel: \"Textarea\",\r\n      textareaPlaceholder: \"Write a comment...\",\r\n      characterCount: \"0/280\",\r\n      post: \"Post\",\r\n      textareaDescription: \"Footer positioned below the textarea.\",\r\n    },\r\n  },\r\n  ar: {\r\n    dir: \"rtl\",\r\n    values: {\r\n      placeholder: \"بحث...\",\r\n      results: \"١٢ نتيجة\",\r\n      searching: \"جاري البحث...\",\r\n      saving: \"جاري الحفظ...\",\r\n      savingChanges: \"جاري حفظ التغييرات...\",\r\n      textareaLabel: \"منطقة النص\",\r\n      textareaPlaceholder: \"اكتب تعليقًا...\",\r\n      characterCount: \"٠/٢٨٠\",\r\n      post: \"نشر\",\r\n      textareaDescription: \"تذييل موضع أسفل منطقة النص.\",\r\n    },\r\n  },\r\n  he: {\r\n    dir: \"rtl\",\r\n    values: {\r\n      placeholder: \"חפש...\",\r\n      results: \"12 תוצאות\",\r\n      searching: \"מחפש...\",\r\n      saving: \"שומר...\",\r\n      savingChanges: \"שומר שינויים...\",\r\n      textareaLabel: \"אזור טקסט\",\r\n      textareaPlaceholder: \"כתוב תגובה...\",\r\n      characterCount: \"0/280\",\r\n      post: \"פרסם\",\r\n      textareaDescription: \"כותרת תחתונה ממוקמת מתחת לאזור הטקסט.\",\r\n    },\r\n  },\r\n};\r\n\r\nexport function InputGroupRtl() {\r\n  const { dir, language, t } = useTranslation(translations, \"ar\");\r\n\r\n  return (\r\n    <div className=\"grid w-full max-w-sm gap-6\" lang={language} dir={dir}>\r\n      <InputGroup className=\"max-w-xs\">\r\n        <InputGroupInput placeholder={t.placeholder} />\r\n        <InputGroupAddon>\r\n          <Search />\r\n        </InputGroupAddon>\r\n        <InputGroupAddon align=\"inline-end\">{t.results}</InputGroupAddon>\r\n      </InputGroup>\r\n      <InputGroup>\r\n        <InputGroupInput placeholder={t.searching} />\r\n        <InputGroupAddon align=\"inline-end\">\r\n          <Spinner />\r\n        </InputGroupAddon>\r\n      </InputGroup>\r\n      <InputGroup>\r\n        <InputGroupInput placeholder={t.savingChanges} />\r\n        <InputGroupAddon align=\"inline-end\">\r\n          <InputGroupText>{t.saving}</InputGroupText>\r\n          <Spinner />\r\n        </InputGroupAddon>\r\n      </InputGroup>\r\n      <FieldGroup className=\"max-w-sm\">\r\n        <Field>\r\n          <FieldLabel htmlFor=\"rtl-textarea\">{t.textareaLabel}</FieldLabel>\r\n          <InputGroup>\r\n            <InputGroupTextarea\r\n              id=\"rtl-textarea\"\r\n              placeholder={t.textareaPlaceholder}\r\n            />\r\n            <InputGroupAddon align=\"block-end\">\r\n              <InputGroupText>{t.characterCount}</InputGroupText>\r\n              <InputGroupButton variant=\"default\" size=\"sm\" className=\"ms-auto\">\r\n                {t.post}\r\n              </InputGroupButton>\r\n            </InputGroupAddon>\r\n          </InputGroup>\r\n          <FieldDescription>{t.textareaDescription}</FieldDescription>\r\n        </Field>\r\n      </FieldGroup>\r\n    </div>\r\n  );\r\n}\r\n",
      "type": "registry:example"
    }
  ],
  "type": "registry:example"
}